discordws/__init__.py
discordws/events.py
discordws/gateway.py
discordws/intents.py
discord_ws-0.0.1.dist-info/LICENSE
discord_ws-0.0.1.dist-info/METADATA
discord_ws-0.0.1.dist-info/WHEEL
discord_ws-0.0.1.dist-info/top_level.txt
discord_ws-0.0.1.dist-info/RECORD
