Metadata-Version: 2.1
Name: discord-ws
Version: 0.0.1
Summary: UNKNOWN
Home-page: UNKNOWN
License: UNKNOWN
Platform: UNKNOWN
Requires-Python: >=3.8.0
License-File: LICENSE
Requires-Dist: websockets
Requires-Dist: altflags
